rabbit_bq_job_optimizer/__init__.py
rabbit_bq_job_optimizer/client.py
rabbit_bq_job_optimizer/exceptions.py
rabbit_bq_job_optimizer/models.py
rabbit_bq_job_optimizer-0.1.16.dist-info/licenses/LICENSE
rabbit_bq_job_optimizer-0.1.16.dist-info/METADATA
rabbit_bq_job_optimizer-0.1.16.dist-info/WHEEL
rabbit_bq_job_optimizer-0.1.16.dist-info/top_level.txt
rabbit_bq_job_optimizer-0.1.16.dist-info/RECORD
