Metadata-Version: 2.4
Name: rabbit-bq-job-optimizer
Version: 0.1.16
Summary: Python client for Rabbit BigQuery Job Optimizer API
Home-page: https://github.com/followrabbit-ai/python-bq-job-optimizer
Author: Rabbit Team
Author-email: success@followrabbit.ai
Classifier: Programming Language :: Python :: 3
Classifier: License :: OSI Approved :: Apache Software License
Classifier: Operating System :: OS Independent
Requires-Python: >=3.8
License-File: LICENSE
Requires-Dist: requests>=2.31.0
Dynamic: author
Dynamic: author-email
Dynamic: classifier
Dynamic: description
Dynamic: description-content-type
Dynamic: home-page
Dynamic: license-file
Dynamic: requires-dist
Dynamic: requires-python
Dynamic: summary
